elasticsearch_partition/__init__.py
elasticsearch_partition/dateutils.c
elasticsearch_partition/dateutils.cpython-37m-darwin.so
elasticsearch_partition/dateutils.pxd
elasticsearch_partition/dateutils.pyx
elasticsearch_partition/formatters.c
elasticsearch_partition/formatters.cpython-37m-darwin.so
elasticsearch_partition/formatters.pxd
elasticsearch_partition/formatters.pyx
elasticsearch_partition/partitioning.c
elasticsearch_partition/partitioning.cpython-37m-darwin.so
elasticsearch_partition/partitioning.pyx
elasticsearch_partition-2.0.0.dist-info/METADATA
elasticsearch_partition-2.0.0.dist-info/RECORD
elasticsearch_partition-2.0.0.dist-info/WHEEL
elasticsearch_partition-2.0.0.dist-info/top_level.txt
