Metadata-Version: 2.1
Name: elasticsearch-partition
Version: 2.0.0
Summary: A Python library for creating Elasticsearch partitioned indexes by date range
Home-page: https://github.com/dmvass/elasticsearch-partition
Author: Dmitri Vasilishin
Author-email: vasilishin.d.o@gmail.com
License: UNKNOWN
Keywords: elasticsearch,partition,cython,bigdata
Platform: UNKNOWN
Classifier: Development Status :: 5 - Production/Stable
Classifier: Intended Audience :: Developers
Classifier: Programming Language :: Python :: Implementation :: CPython
Classifier: Programming Language :: Python :: Implementation :: PyPy
Classifier: Programming Language :: Python :: 2
Classifier: Programming Language :: Python :: 2.7
Classifier: Programming Language :: Python :: 3
Classifier: Programming Language :: Python :: 3.5
Classifier: Programming Language :: Python :: 3.6
Classifier: Programming Language :: Python :: 3.7
Classifier: License :: OSI Approved :: MIT License
Classifier: Operating System :: OS Independent
Provides-Extra: dev
Requires-Dist: cython
Provides-Extra: dev
Requires-Dist: tox; extra == 'dev'
Requires-Dist: bumpversion; extra == 'dev'
